pyghostdb/__init__.py
pyghostdb/ghost_storage.py
pyghostdb/hnswlib_index.py
pyghostdb/parquet_conversion.py
pyghostdb/test_hnsw.py
pyghostdb/text_storage.py
pyghostdb-0.0.5.dist-info/METADATA
pyghostdb-0.0.5.dist-info/WHEEL
pyghostdb-0.0.5.dist-info/top_level.txt
pyghostdb-0.0.5.dist-info/RECORD
